aigar/__init__.py
aigar/envs/__init__.py
aigar/envs/aigarEnv.py
aigar/envs/controller/__init__.py
aigar/envs/controller/controller.py
aigar/envs/model/__init__.py
aigar/envs/model/bot.py
aigar/envs/model/cell.py
aigar/envs/model/field.py
aigar/envs/model/parameters.py
aigar/envs/model/player.py
aigar/envs/model/rgbGenerator.py
aigar/envs/model/spatialHashTable.py
aigar/envs/view/__init__.py
aigar/envs/view/startScreen.py
aigar/envs/view/view.py
aigar-0.0.2.dist-info/LICENSE
aigar-0.0.2.dist-info/METADATA
aigar-0.0.2.dist-info/WHEEL
aigar-0.0.2.dist-info/top_level.txt
aigar-0.0.2.dist-info/RECORD
