Metadata-Version: 2.1
Name: aigar
Version: 0.0.2
Summary: Gym-compatible environments that replicate the aigar.io game to a certain extent.
Home-page: https://github.com/NotNANtoN/aigar
Author: Anton Wiehe
Author-email: antonwiehe@gmail.com
License: MIT
Keywords: reinforcement learning,environments,gym
Platform: UNKNOWN
Classifier: Programming Language :: Python :: 3
Classifier: License :: OSI Approved :: GNU General Public License v3 (GPLv3)
Classifier: Operating System :: OS Independent
Requires-Dist: gym
Requires-Dist: pygame
Requires-Dist: numpy
